blue_dot_sessions.color.toml
gemscapes/__init__.py
gemscapes/__main__.py
gemscapes/audio/__init__.py
gemscapes/audio/audio_processor.py
gemscapes/audio/get_max_level.py
gemscapes/audio/get_sound_type.py
gemscapes/audio/loudnorm.py
gemscapes/audio/pysndfile_wrapper.py
gemscapes/audio/samples_to_seconds.py
gemscapes/audio/sndfile.py
gemscapes/audio_visualizer.py
gemscapes/color/__init__.py
gemscapes/color/color_schemes.py
gemscapes/color/interpolate_colors.py
gemscapes/color/util.py
gemscapes/color/visualize_color_scheme.py
gemscapes/conversion/__init__.py
gemscapes/exceptions.py
gemscapes/image/__init__.py
gemscapes/image/spectrogram_image.py
gemscapes/image/waveform_image.py
gemscapes/metadata/__init__.py
gemscapes/metadata/__main__.py
gemscapes/pipeline/__init__.py
gemscapes/pipeline/compute_stats.py
gemscapes/pipeline/convert.py
gemscapes/pipeline/pipeline_types.py
gemscapes/pipeline/post_primitive.py
gemscapes/pipeline/post_wav2png.py
gemscapes/pipeline/primitive.py
gemscapes/pipeline/wav2png.py
gemscapes/plotting/__init__.py
gemscapes/stats.py
gemscapes/svg_tools/__init__.py
gemscapes/svg_tools/__main__.py
gemscapes/svg_tools/sandbox.py
gemscapes/svg_tools/util.py
blue_dot_sessions_gemscapes-1.8.0.dist-info/LICENSE
blue_dot_sessions_gemscapes-1.8.0.dist-info/WHEEL
blue_dot_sessions_gemscapes-1.8.0.dist-info/METADATA
blue_dot_sessions_gemscapes-1.8.0.dist-info/RECORD
